{
    "cards": {
        "2C" : "../media/cards/2_of_clubs.png",
        "2D" : "../media/cards/2_of_diamonds.png",
        "2H" : "../media/cards/2_of_hearts.png",
        "2S" : "../media/cards/2_of_spades.png",
        "3C" : "../media/cards/3_of_clubs.png",
        "3D" : "../media/cards/3_of_diamonds.png",
        "3H" : "../media/cards/3_of_hearts.png",
        "3S" : "../media/cards/3_of_spades.png",
        "4C" : "../media/cards/4_of_clubs.png",
        "4D" : "../media/cards/4_of_diamonds.png",
        "4H" : "../media/cards/4_of_hearts.png",
        "4S" : "../media/cards/4_of_spades.png",
        "5C" : "../media/cards/5_of_clubs.png",
        "5D" : "../media/cards/5_of_diamonds.png",
        "5H" : "../media/cards/5_of_hearts.png",
        "5S" : "../media/cards/5_of_spades.png",
        "6C" : "../media/cards/6_of_clubs.png",
        "6D" : "../media/cards/6_of_diamonds.png",
        "6H" : "../media/cards/6_of_hearts.png",
        "6S" : "../media/cards/6_of_spades.png",
        "7C" : "../media/cards/7_of_clubs.png",
        "7D" : "../media/cards/7_of_diamonds.png",
        "7H" : "../media/cards/7_of_hearts.png",
        "7S" : "../media/cards/7_of_spades.png",
        "8C" : "../media/cards/8_of_clubs.png",
        "8D" : "../media/cards/8_of_diamonds.png",
        "8H" : "../media/cards/8_of_hearts.png",
        "8S" : "../media/cards/8_of_spades.png",
        "9C" : "../media/cards/9_of_clubs.png",
        "9D" : "../media/cards/9_of_diamonds.png",
        "9H" : "../media/cards/9_of_hearts.png",
        "9S" : "../media/cards/9_of_spades.png",
        "10C" : "../media/cards/10_of_clubs.png",
        "10D" : "../media/cards/10_of_diamonds.png",
        "10H" : "../media/cards/10_of_hearts.png",
        "10S" : "../media/cards/10_of_spades.png",
        "JC" : "../media/cards/jack_of_clubs.png",
        "JD" : "../media/cards/jack_of_diamonds.png",
        "JH" : "../media/cards/jack_of_hearts.png",
        "JS" : "../media/cards/jack_of_spades.png",
        "QC" : "../media/cards/queen_of_clubs.png",
        "QD" : "../media/cards/queen_of_diamonds.png",
        "QH" : "../media/cards/queen_of_hearts.png",
        "QS" : "../media/cards/queen_of_spades.png",
        "KC" : "../media/cards/king_of_clubs.png",
        "KD" : "../media/cards/king_of_diamonds.png",
        "KH" : "../media/cards/king_of_hearts.png",
        "KS" : "../media/cards/king_of_spades.png",
        "AC" : "../media/cards/ace_of_clubs.png",
        "AD" : "../media/cards/ace_of_diamonds.png",
        "AH" : "../media/cards/ace_of_hearts.png",
        "AS" : "../media/cards/ace_of_spades.png"
    },
    "jokers" : {
        "blueprint" : "../media/cards/blueprint.png",
        "baseball_card" : "../media/cards/baseball_card.png",
        "joker" : "../media/cards/joker.png"
    }
}